etsi_qkd_014_client/__init__.py
etsi_qkd_014_client/cli.py
etsi_qkd_014_client/client.py
etsi_qkd_014_client/data.py
etsi_qkd_014_client-0.9.0.dist-info/entry_points.txt
etsi_qkd_014_client-0.9.0.dist-info/LICENSE
etsi_qkd_014_client-0.9.0.dist-info/WHEEL
etsi_qkd_014_client-0.9.0.dist-info/METADATA
etsi_qkd_014_client-0.9.0.dist-info/RECORD
