Metadata-Version: 2.1
Name: etsi-qkd-014-client
Version: 0.9.0
Summary: A Python client for the QKD 014 standard
Home-page: https://github.com/nanoy42/etsi-qkd-014-client
License: LGPL-3.0-or-later
Keywords: qkd,etsi-qkd-014,python client
Author: Yoann Piétri
Author-email: Yoann.Pietri@lip6.fr
Requires-Python: >=3.7.2,<4
Classifier: Development Status :: 4 - Beta
Classifier: Intended Audience :: Science/Research
Classifier: Intended Audience :: Telecommunications Industry
Classifier: License :: OSI Approved :: GNU Lesser General Public License v3 or later (LGPLv3+)
Classifier: Programming Language :: Python
Classifier: Programming Language :: Python :: 3
Classifier: Programming Language :: Python :: 3.8
Classifier: Programming Language :: Python :: 3.9
Classifier: Programming Language :: Python :: 3.10
Classifier: Programming Language :: Python :: 3.11
Classifier: Topic :: Scientific/Engineering :: Interface Engine/Protocol Translator
Requires-Dist: requests (>=2.28.1,<3.0.0)
Project-URL: Documentation, https://etsi-qkd-014-client.readthedocs.io/en/latest/
Project-URL: Repository, https://github.com/nanoy42/etsi-qkd-014-client
